cacheing/__init__.py
cacheing/utils.py
cacheing-0.1.1.dist-info/LICENSE
cacheing-0.1.1.dist-info/WHEEL
cacheing-0.1.1.dist-info/METADATA
cacheing-0.1.1.dist-info/RECORD
