Metadata-Version: 2.1
Name: cacheing
Version: 0.1.1
Summary: a performant python cacheing library
Home-page: https://github.com/breid48/cacheing
License: MIT
Author: Blake Reid
Author-email: breid48@uwo.ca
Requires-Python: >=3.8,<4.0
Classifier: License :: OSI Approved :: MIT License
Classifier: Operating System :: MacOS
Classifier: Operating System :: Microsoft :: Windows :: Windows 10
Classifier: Operating System :: Microsoft :: Windows :: Windows 11
Classifier: Operating System :: POSIX :: Linux
Classifier: Programming Language :: Python :: 3
Classifier: Programming Language :: Python :: 3.8
Classifier: Programming Language :: Python :: 3.9
Classifier: Programming Language :: Python :: 3.10
Classifier: Programming Language :: Python :: 3.11
Classifier: Programming Language :: Python :: 3
Classifier: Topic :: Software Development :: Libraries :: Python Modules
Project-URL: Bug Tracker, https://github.com/breid48/cacheing/issues/
Project-URL: Repository, https://github.com/breid48/cacheing
